oauth2/__init__.py
oauth2/client_authenticator.py
oauth2/compatibility.py
oauth2/datatype.py
oauth2/error.py
oauth2/grant.py
oauth2/log.py
oauth2/tokengenerator.py
oauth2/store/__init__.py
oauth2/store/dynamodb.py
oauth2/store/memcache.py
oauth2/store/memory.py
oauth2/store/mongodb.py
oauth2/store/redisdb.py
oauth2/store/stateless.py
oauth2/store/dbapi/__init__.py
oauth2/store/dbapi/mysql.py
oauth2/test/__init__.py
oauth2/test/test_client_authenticator.py
oauth2/test/test_datatype.py
oauth2/test/test_grant.py
oauth2/test/test_oauth2.py
oauth2/test/test_tokengenerator.py
oauth2/test/test_web.py
oauth2/test/functional/__init__.py
oauth2/test/functional/test_authorization_code.py
oauth2/test/store/__init__.py
oauth2/test/store/test_dbapi.py
oauth2/test/store/test_memcache.py
oauth2/test/store/test_memory.py
oauth2/test/store/test_mongodb.py
oauth2/test/store/test_redisdb.py
oauth2/web/__init__.py
oauth2/web/aiohttp.py
oauth2/web/flask.py
oauth2/web/tornado.py
oauth2/web/wsgi.py
oauth2_stateless-1.1.0.dist-info/DESCRIPTION.rst
oauth2_stateless-1.1.0.dist-info/METADATA
oauth2_stateless-1.1.0.dist-info/RECORD
oauth2_stateless-1.1.0.dist-info/WHEEL
oauth2_stateless-1.1.0.dist-info/metadata.json
oauth2_stateless-1.1.0.dist-info/top_level.txt
