Metadata-Version: 2.0
Name: oauth2-stateless
Version: 1.1.0
Summary: OAuth 2.0 provider for python with Stateless tokens support
Home-page: https://github.com/darkanthey/oauth2-stateless
Author: Andrew Grytsenko
Author-email: darkanthey@gmail.com
License: UNKNOWN
Platform: UNKNOWN
Classifier: Development Status :: 4 - Beta
Classifier: License :: OSI Approved :: MIT License
Classifier: Programming Language :: Python :: 2
Classifier: Programming Language :: Python :: 2.7
Classifier: Programming Language :: Python :: 3
Classifier: Programming Language :: Python :: 3.4
Classifier: Programming Language :: Python :: 3.5
Classifier: Programming Language :: Python :: 3.6
Requires-Dist: ujson
Requires-Dist: itsdangerous
Provides-Extra: memcache
Requires-Dist: python-memcached; extra == 'memcache'
Provides-Extra: mongodb
Requires-Dist: pymongo; extra == 'mongodb'
Provides-Extra: redis
Requires-Dist: redis; extra == 'redis'
